[{"__symbolic":"module","version":4,"metadata":{"ReportViewerComponent":{"__symbolic":"class","decorators":[{"__symbolic":"call","expression":{"__symbolic":"reference","module":"@angular/core","name":"Component","line":6,"character":1},"arguments":[{"selector":"ssrs-reportviewer","templateUrl":"./reportviewer.component.html","styleUrls":["./reportviewer.component.css"]}]}],"members":{"iframe":[{"__symbolic":"property","decorators":[{"__symbolic":"call","expression":{"__symbolic":"reference","module":"@angular/core","name":"ViewChild","line":12,"character":3},"arguments":["iframe"]}]}],"reporturl":[{"__symbolic":"property","decorators":[{"__symbolic":"call","expression":{"__symbolic":"reference","module":"@angular/core","name":"Input","line":14,"character":3}}]}],"reportserver":[{"__symbolic":"property","decorators":[{"__symbolic":"call","expression":{"__symbolic":"reference","module":"@angular/core","name":"Input","line":16,"character":3}}]}],"showparameters":[{"__symbolic":"property","decorators":[{"__symbolic":"call","expression":{"__symbolic":"reference","module":"@angular/core","name":"Input","line":18,"character":3}}]}],"parameters":[{"__symbolic":"property","decorators":[{"__symbolic":"call","expression":{"__symbolic":"reference","module":"@angular/core","name":"Input","line":20,"character":3}}]}],"language":[{"__symbolic":"property","decorators":[{"__symbolic":"call","expression":{"__symbolic":"reference","module":"@angular/core","name":"Input","line":22,"character":3}}]}],"width":[{"__symbolic":"property","decorators":[{"__symbolic":"call","expression":{"__symbolic":"reference","module":"@angular/core","name":"Input","line":24,"character":3}}]}],"height":[{"__symbolic":"property","decorators":[{"__symbolic":"call","expression":{"__symbolic":"reference","module":"@angular/core","name":"Input","line":26,"character":3}}]}],"toolbar":[{"__symbolic":"property","decorators":[{"__symbolic":"call","expression":{"__symbolic":"reference","module":"@angular/core","name":"Input","line":28,"character":3}}]}],"onError":[{"__symbolic":"property","decorators":[{"__symbolic":"call","expression":{"__symbolic":"reference","module":"@angular/core","name":"Output","line":32,"character":3},"arguments":["error"]}]}],"__ctor__":[{"__symbolic":"constructor","parameters":[{"__symbolic":"reference","module":"@angular/platform-browser","name":"DomSanitizer","line":33,"character":33},{"__symbolic":"reference","module":"@angular/common/http","name":"HttpClient","line":33,"character":61}]}],"ngOnChanges":[{"__symbolic":"method"}],"createAuthorizationHeader":[{"__symbolic":"method"}],"get":[{"__symbolic":"method"}],"buildParameterString":[{"__symbolic":"method"}],"buildReportUrl":[{"__symbolic":"method"}]}}}}]